README.rst
setup.cfg
setup.py
devdocs_cli/__init__.py
devdocs_cli/alfred.py
devdocs_cli/cli.py
devdocs_cli/config.py
devdocs_cli/devdocs.py
devdocs_cli.egg-info/PKG-INFO
devdocs_cli.egg-info/SOURCES.txt
devdocs_cli.egg-info/dependency_links.txt
devdocs_cli.egg-info/entry_points.txt
devdocs_cli.egg-info/requires.txt
devdocs_cli.egg-info/top_level.txt