Metadata-Version: 1.1
Name: devdocs-cli
Version: 0.0.2
Summary: Devdocs integration for alfred
Home-page: https://github.com/kdeal/devdocs-cli
Author: Kyle Deal
Author-email: kdeal@kyledeal.com
License: UNKNOWN
Platform: UNKNOWN
Classifier: Development Status :: 2 - Pre-Alpha
Classifier: Programming Language :: Python
Classifier: Programming Language :: Python :: 2
Classifier: Programming Language :: Python :: 2.7
Classifier: Programming Language :: Python :: 3
Classifier: Programming Language :: Python :: 3.4
Classifier: Programming Language :: Python :: 3.5
